MANIFEST.in
README.md
setup.cfg
setup.py
bin/__init__.py
bin/bitwallet
bitwallet/__init__.py
bitwallet/currency_utils.py
bitwallet/exchanges.py
bitwallet/fiat.py
bitwallet/wallet.py
bitwallet.egg-info/PKG-INFO
bitwallet.egg-info/SOURCES.txt
bitwallet.egg-info/dependency_links.txt
bitwallet.egg-info/requires.txt
bitwallet.egg-info/top_level.txt