Metadata-Version: 1.1
Name: bitwallet
Version: 1.0.8
Summary: Python Wallet that enables P&L
Home-page: https://github.com/lookfwd/bitwallet
Author: Dimitrios Kouzis-Loukas
Author-email: lookfwd@gmail.com
License: UNKNOWN
Platform: UNKNOWN
Classifier: Programming Language :: Python
Classifier: Programming Language :: Python :: 2.7
Classifier: Operating System :: OS Independent
Classifier: License :: OSI Approved :: MIT License
Classifier: Development Status :: 5 - Production/Stable
Classifier: Topic :: Office/Business :: Financial
